xia_git_gitlab/__init__.py
xia_git_gitlab/git.cpython-39-darwin.so
xia_git_gitlab-0.1.24.dist-info/LICENSE.txt
xia_git_gitlab-0.1.24.dist-info/METADATA
xia_git_gitlab-0.1.24.dist-info/WHEEL
xia_git_gitlab-0.1.24.dist-info/top_level.txt
xia_git_gitlab-0.1.24.dist-info/RECORD
