Metadata-Version: 2.1
Name: xia-git-gitlab
Version: 0.1.24
Home-page: https://develop.x-i-a.com/docs/xia-git-gitlab/0.1.24/index.html
Author: X-I-A
Author-email: admin@x-i-a.com
Requires-Python: >=3.9
License-File: LICENSE.txt
Requires-Dist: requests
Requires-Dist: GitPython
Requires-Dist: xia-git
